README.md
setup.cfg
setup.py
libjournal/__init__.py
libjournal/libj.py
libjournal/libj_json.py
libjournal.egg-info/PKG-INFO
libjournal.egg-info/SOURCES.txt
libjournal.egg-info/dependency_links.txt
libjournal.egg-info/not-zip-safe
libjournal.egg-info/requires.txt
libjournal.egg-info/top_level.txt