Metadata-Version: 1.1
Name: libjournal
Version: 2.0.0
Summary: A library that allows you to create, delete, and read journal entries
Home-page: https://github.com/undystopia/libjournal
Author: Aneesh Edara, Aviral Mishra
Author-email: kiwipop@kiwipop.me
License: GNU
Download-URL: https://github.com/nitroignika/libjournal/archive/2.0.0.tar.gz
Keywords: journal,libj,libjournal
Platform: UNKNOWN
